[{"City":"ALTAMONTE SPRINGS","Zipcode":"32714","SubDivision":"SAN SEBASTIAN HEIGHTS","PreFlip":{"NumHouses":2.0,"Price":140000.0,"Beds":4.0,"FullBaths":2.0,"HalfBaths":0.0,"SqFtHeated":1938.0,"YearBuilt":1972.0},"PostFlip":{"NumHouses":2.0,"Price":242000.0,"Beds":4.0,"FullBaths":2.0,"HalfBaths":0.0,"SqFtHeated":1938.0,"YearBuilt":1972.0},"RoiPurchase":0.0,"RoiSold":0.0},{"City":"ALTAMONTE SPRINGS","Zipcode":"32714","SubDivision":"SPRING OAKS","PreFlip":{"NumHouses":6.0,"Price":150133.33,"Beds":3.0,"FullBaths":2.0,"HalfBaths":0.0,"SqFtHeated":1352.0,"YearBuilt":1316.0},"PostFlip":{"NumHouses":6.0,"Price":213375.0,"Beds":3.0,"FullBaths":2.0,"HalfBaths":0.0,"SqFtHeated":1352.0,"YearBuilt":1316.0},"RoiPurchase":0.0,"RoiSold":0.0},{"City":"APOPKA","Zipcode":"32703","SubDivision":"SHEELER OAKS","PreFlip":{"NumHouses":2.0,"Price":88100.0,"Beds":2.0,"FullBaths":2.0,"HalfBaths":0.0,"SqFtHeated":1326.0,"YearBuilt":1987.0},"PostFlip":{"NumHouses":2.0,"Price":161500.0,"Beds":3.0,"FullBaths":2.0,"HalfBaths":0.0,"SqFtHeated":1428.0,"YearBuilt":1987.0},"RoiPurchase":0.0,"RoiSold":0.0},{"City":"CASSELBERRY","Zipcode":"32707","SubDivision":"CARRIAGE HILL","PreFlip":{"NumHouses":2.0,"Price":117250.0,"Beds":3.0,"FullBaths":2.0,"HalfBaths":0.0,"SqFtHeated":1376.0,"YearBuilt":1969.0},"PostFlip":{"NumHouses":2.0,"Price":205850.0,"Beds":4.0,"FullBaths":2.0,"HalfBaths":0.0,"SqFtHeated":1425.0,"YearBuilt":1969.0},"RoiPurchase":0.0,"RoiSold":0.0},{"City":"CASSELBERRY","Zipcode":"32707","SubDivision":"COLONNADES","PreFlip":{"NumHouses":2.0,"Price":47000.0,"Beds":3.0,"FullBaths":2.0,"HalfBaths":0.0,"SqFtHeated":1022.0,"YearBuilt":1978.0},"PostFlip":{"NumHouses":2.0,"Price":118250.0,"Beds":3.0,"FullBaths":2.0,"HalfBaths":0.0,"SqFtHeated":1028.0,"YearBuilt":1978.0},"RoiPurchase":0.0,"RoiSold":0.0},{"City":"CASSELBERRY","Zipcode":"32707","SubDivision":"DEER RUN","PreFlip":{"NumHouses":3.0,"Price":127312.67,"Beds":1.0,"FullBaths":1.0,"HalfBaths":0.0,"SqFtHeated":859.0,"YearBuilt":1322.0},"PostFlip":{"NumHouses":3.0,"Price":181633.33,"Beds":2.0,"FullBaths":1.0,"HalfBaths":0.0,"SqFtHeated":859.0,"YearBuilt":1322.0},"RoiPurchase":0.0,"RoiSold":0.0},{"City":"CASSELBERRY","Zipcode":"32707","SubDivision":"HOWELL COVE","PreFlip":{"NumHouses":3.0,"Price":150219.33,"Beds":2.0,"FullBaths":1.0,"HalfBaths":0.0,"SqFtHeated":1347.0,"YearBuilt":1319.0},"PostFlip":{"NumHouses":3.0,"Price":256000.0,"Beds":2.0,"FullBaths":1.0,"HalfBaths":0.0,"SqFtHeated":1347.0,"YearBuilt":1319.0},"RoiPurchase":0.0,"RoiSold":0.0},{"City":"CASSELBERRY","Zipcode":"32707","SubDivision":"ORANGE GROVE PARK","PreFlip":{"NumHouses":2.0,"Price":136394.5,"Beds":3.0,"FullBaths":2.0,"HalfBaths":0.0,"SqFtHeated":1300.0,"YearBuilt":1986.0},"PostFlip":{"NumHouses":2.0,"Price":184500.0,"Beds":3.0,"FullBaths":2.0,"HalfBaths":0.0,"SqFtHeated":1300.0,"YearBuilt":1986.0},"RoiPurchase":0.0,"RoiSold":0.0},{"City":"CASSELBERRY","Zipcode":"32707","SubDivision":"QUEENS MIRROR SOUTH","PreFlip":{"NumHouses":3.0,"Price":78190.0,"Beds":2.0,"FullBaths":1.0,"HalfBaths":0.0,"SqFtHeated":768.0,"YearBuilt":1305.0},"PostFlip":{"NumHouses":3.0,"Price":144933.33,"Beds":2.0,"FullBaths":1.0,"HalfBaths":0.0,"SqFtHeated":768.0,"YearBuilt":1305.0},"RoiPurchase":0.0,"RoiSold":0.0},{"City":"CASSELBERRY","Zipcode":"32707","SubDivision":"SEMINOLE SITES","PreFlip":{"NumHouses":2.0,"Price":87034.0,"Beds":3.0,"FullBaths":2.0,"HalfBaths":0.0,"SqFtHeated":1213.0,"YearBuilt":1976.0},"PostFlip":{"NumHouses":2.0,"Price":155500.0,"Beds":3.0,"FullBaths":2.0,"HalfBaths":0.0,"SqFtHeated":1342.0,"YearBuilt":1976.0},"RoiPurchase":0.0,"RoiSold":0.0},{"City":"KISSIMMEE","Zipcode":"34743","SubDivision":"BUENAVENTURA LAKES","PreFlip":{"NumHouses":11.0,"Price":109947.18,"Beds":3.0,"FullBaths":2.0,"HalfBaths":0.0,"SqFtHeated":1263.0,"YearBuilt":1623.0},"PostFlip":{"NumHouses":11.0,"Price":163526.36,"Beds":3.0,"FullBaths":2.0,"HalfBaths":0.0,"SqFtHeated":1291.0,"YearBuilt":1623.0},"RoiPurchase":0.0,"RoiSold":0.0},{"City":"KISSIMMEE","Zipcode":"34746","SubDivision":"INDIAN POINT","PreFlip":{"NumHouses":2.0,"Price":122450.0,"Beds":3.0,"FullBaths":2.0,"HalfBaths":0.0,"SqFtHeated":1265.0,"YearBuilt":1995.0},"PostFlip":{"NumHouses":2.0,"Price":152500.0,"Beds":3.0,"FullBaths":2.0,"HalfBaths":0.0,"SqFtHeated":1265.0,"YearBuilt":1995.0},"RoiPurchase":0.0,"RoiSold":0.0},{"City":"KISSIMMEE","Zipcode":"34747","SubDivision":"INDIAN RIDGE","PreFlip":{"NumHouses":2.0,"Price":121000.0,"Beds":3.0,"FullBaths":2.0,"HalfBaths":0.0,"SqFtHeated":1568.0,"YearBuilt":1988.0},"PostFlip":{"NumHouses":2.0,"Price":188000.0,"Beds":3.0,"FullBaths":2.0,"HalfBaths":0.0,"SqFtHeated":1568.0,"YearBuilt":1988.0},"RoiPurchase":0.0,"RoiSold":0.0},{"City":"KISSIMMEE","Zipcode":"34744","SubDivision":"MILL RUN","PreFlip":{"NumHouses":3.0,"Price":114416.67,"Beds":3.0,"FullBaths":2.0,"HalfBaths":0.0,"SqFtHeated":1430.0,"YearBuilt":1985.0},"PostFlip":{"NumHouses":3.0,"Price":175707.0,"Beds":3.0,"FullBaths":2.0,"HalfBaths":0.0,"SqFtHeated":1430.0,"YearBuilt":1985.0},"RoiPurchase":0.0,"RoiSold":0.0},{"City":"KISSIMMEE","Zipcode":"34758, 34759","SubDivision":"POINCIANA VILLAGE","PreFlip":{"NumHouses":13.0,"Price":77660.31,"Beds":2.0,"FullBaths":1.0,"HalfBaths":0.0,"SqFtHeated":842.0,"YearBuilt":1224.0},"PostFlip":{"NumHouses":13.0,"Price":119386.69,"Beds":2.0,"FullBaths":1.0,"HalfBaths":0.0,"SqFtHeated":842.0,"YearBuilt":1224.0},"RoiPurchase":0.0,"RoiSold":0.0},{"City":"LAKE MARY","Zipcode":"32746","SubDivision":"CROSSINGS","PreFlip":{"NumHouses":2.0,"Price":193000.0,"Beds":4.0,"FullBaths":2.0,"HalfBaths":0.0,"SqFtHeated":2062.0,"YearBuilt":1988.0},"PostFlip":{"NumHouses":2.0,"Price":264000.0,"Beds":4.0,"FullBaths":2.0,"HalfBaths":0.0,"SqFtHeated":2062.0,"YearBuilt":1988.0},"RoiPurchase":0.0,"RoiSold":0.0},{"City":"LAKELAND","Zipcode":"33811","SubDivision":"FORESTGREEN","PreFlip":{"NumHouses":2.0,"Price":90350.0,"Beds":3.0,"FullBaths":2.0,"HalfBaths":0.0,"SqFtHeated":1707.0,"YearBuilt":1981.0},"PostFlip":{"NumHouses":2.0,"Price":174500.0,"Beds":3.0,"FullBaths":2.0,"HalfBaths":0.0,"SqFtHeated":2049.0,"YearBuilt":1981.0},"RoiPurchase":0.0,"RoiSold":0.0},{"City":"LAKELAND","Zipcode":"33801","SubDivision":"HONEYTREE","PreFlip":{"NumHouses":3.0,"Price":68666.67,"Beds":2.0,"FullBaths":1.0,"HalfBaths":0.0,"SqFtHeated":861.0,"YearBuilt":1323.0},"PostFlip":{"NumHouses":3.0,"Price":122950.0,"Beds":2.0,"FullBaths":1.0,"HalfBaths":0.0,"SqFtHeated":861.0,"YearBuilt":1323.0},"RoiPurchase":0.0,"RoiSold":0.0},{"City":"LAKELAND","Zipcode":"33813","SubDivision":"INDIAN TRAILS","PreFlip":{"NumHouses":2.0,"Price":131325.0,"Beds":4.0,"FullBaths":2.0,"HalfBaths":0.0,"SqFtHeated":1578.0,"YearBuilt":1980.0},"PostFlip":{"NumHouses":2.0,"Price":171500.0,"Beds":4.0,"FullBaths":2.0,"HalfBaths":0.0,"SqFtHeated":1578.0,"YearBuilt":1980.0},"RoiPurchase":0.0,"RoiSold":0.0},{"City":"LAKELAND","Zipcode":"33812, 33813","SubDivision":"W F HALLAM & COS FARMING & TRUCKING LANDS","PreFlip":{"NumHouses":2.0,"Price":82275.0,"Beds":3.0,"FullBaths":2.0,"HalfBaths":0.0,"SqFtHeated":1520.0,"YearBuilt":1980.0},"PostFlip":{"NumHouses":2.0,"Price":165250.0,"Beds":4.0,"FullBaths":2.0,"HalfBaths":0.0,"SqFtHeated":1696.0,"YearBuilt":1980.0},"RoiPurchase":0.0,"RoiSold":0.0},{"City":"LAKELAND","Zipcode":"33811","SubDivision":"WILDWOOD","PreFlip":{"NumHouses":2.0,"Price":62425.0,"Beds":3.0,"FullBaths":2.0,"HalfBaths":0.0,"SqFtHeated":1206.0,"YearBuilt":1986.0},"PostFlip":{"NumHouses":2.0,"Price":119250.0,"Beds":3.0,"FullBaths":2.0,"HalfBaths":0.0,"SqFtHeated":1206.0,"YearBuilt":1986.0},"RoiPurchase":0.0,"RoiSold":0.0},{"City":"LONGWOOD","Zipcode":"32701, 32750","SubDivision":"SANLANDO","PreFlip":{"NumHouses":4.0,"Price":132637.5,"Beds":2.0,"FullBaths":1.0,"HalfBaths":0.0,"SqFtHeated":895.0,"YearBuilt":985.0},"PostFlip":{"NumHouses":4.0,"Price":218475.0,"Beds":2.0,"FullBaths":1.0,"HalfBaths":0.0,"SqFtHeated":895.0,"YearBuilt":985.0},"RoiPurchase":0.0,"RoiSold":0.0},{"City":"LONGWOOD","Zipcode":"33811, 32779","SubDivision":"SWEETWATER","PreFlip":{"NumHouses":2.0,"Price":186000.0,"Beds":4.0,"FullBaths":2.0,"HalfBaths":0.0,"SqFtHeated":2494.0,"YearBuilt":1980.0},"PostFlip":{"NumHouses":2.0,"Price":296500.0,"Beds":4.0,"FullBaths":2.0,"HalfBaths":0.0,"SqFtHeated":2494.0,"YearBuilt":1980.0},"RoiPurchase":0.0,"RoiSold":0.0},{"City":"LONGWOOD","Zipcode":"32712, 32779","SubDivision":"WEKIVA","PreFlip":{"NumHouses":4.0,"Price":155950.0,"Beds":3.0,"FullBaths":2.0,"HalfBaths":0.0,"SqFtHeated":1311.0,"YearBuilt":1484.0},"PostFlip":{"NumHouses":4.0,"Price":248000.0,"Beds":3.0,"FullBaths":2.0,"HalfBaths":0.0,"SqFtHeated":1322.0,"YearBuilt":1484.0},"RoiPurchase":0.0,"RoiSold":0.0},{"City":"MAITLAND","Zipcode":"32751","SubDivision":"ENGLISH ESTATES","PreFlip":{"NumHouses":3.0,"Price":167933.33,"Beds":3.0,"FullBaths":1.0,"HalfBaths":0.0,"SqFtHeated":1293.0,"YearBuilt":1309.0},"PostFlip":{"NumHouses":3.0,"Price":276666.67,"Beds":3.0,"FullBaths":1.0,"HalfBaths":0.0,"SqFtHeated":1327.0,"YearBuilt":1309.0},"RoiPurchase":0.0,"RoiSold":0.0},{"City":"MULBERRY","Zipcode":"32701, 33898, 33810, 33860","SubDivision":"ACREAGE","PreFlip":{"NumHouses":4.0,"Price":127518.75,"Beds":3.0,"FullBaths":2.0,"HalfBaths":0.0,"SqFtHeated":1511.0,"YearBuilt":1966.0},"PostFlip":{"NumHouses":4.0,"Price":193000.0,"Beds":3.0,"FullBaths":2.0,"HalfBaths":0.0,"SqFtHeated":1631.0,"YearBuilt":1966.0},"RoiPurchase":0.0,"RoiSold":0.0},{"City":"MULBERRY","Zipcode":"33860","SubDivision":"IMPERIALAKES","PreFlip":{"NumHouses":3.0,"Price":77916.67,"Beds":2.0,"FullBaths":1.0,"HalfBaths":0.0,"SqFtHeated":1056.0,"YearBuilt":1320.0},"PostFlip":{"NumHouses":3.0,"Price":139166.67,"Beds":2.0,"FullBaths":1.0,"HalfBaths":0.0,"SqFtHeated":1054.0,"YearBuilt":1320.0},"RoiPurchase":0.0,"RoiSold":0.0},{"City":"OCOEE","Zipcode":"34761","SubDivision":"SILVER BEND","PreFlip":{"NumHouses":2.0,"Price":125872.0,"Beds":4.0,"FullBaths":2.0,"HalfBaths":0.0,"SqFtHeated":1735.0,"YearBuilt":1993.0},"PostFlip":{"NumHouses":2.0,"Price":200000.0,"Beds":4.0,"FullBaths":2.0,"HalfBaths":0.0,"SqFtHeated":1735.0,"YearBuilt":1993.0},"RoiPurchase":0.0,"RoiSold":0.0},{"City":"OCOEE","Zipcode":"34761","SubDivision":"TWIN LAKES MANOR","PreFlip":{"NumHouses":2.0,"Price":80750.0,"Beds":3.0,"FullBaths":2.0,"HalfBaths":0.0,"SqFtHeated":1198.0,"YearBuilt":1977.0},"PostFlip":{"NumHouses":2.0,"Price":150000.0,"Beds":3.0,"FullBaths":2.0,"HalfBaths":0.0,"SqFtHeated":1198.0,"YearBuilt":1977.0},"RoiPurchase":0.0,"RoiSold":0.0},{"City":"ORLANDO","Zipcode":"33830, 32807, 32822","SubDivision":"AZALEA PARK","PreFlip":{"NumHouses":7.0,"Price":74494.29,"Beds":3.0,"FullBaths":2.0,"HalfBaths":0.0,"SqFtHeated":1198.0,"YearBuilt":1676.0},"PostFlip":{"NumHouses":7.0,"Price":145785.71,"Beds":3.0,"FullBaths":2.0,"HalfBaths":0.0,"SqFtHeated":1222.0,"YearBuilt":1676.0},"RoiPurchase":0.0,"RoiSold":0.0},{"City":"ORLANDO","Zipcode":"34744, 32822","SubDivision":"BRECKENRIDGE","PreFlip":{"NumHouses":3.0,"Price":134441.67,"Beds":2.0,"FullBaths":2.0,"HalfBaths":0.0,"SqFtHeated":1412.0,"YearBuilt":1325.0},"PostFlip":{"NumHouses":3.0,"Price":193300.0,"Beds":2.0,"FullBaths":2.0,"HalfBaths":0.0,"SqFtHeated":1422.0,"YearBuilt":1325.0},"RoiPurchase":0.0,"RoiSold":0.0},{"City":"ORLANDO","Zipcode":"32829","SubDivision":"CHICKASAW OAKS","PreFlip":{"NumHouses":2.0,"Price":109422.0,"Beds":3.0,"FullBaths":2.0,"HalfBaths":0.0,"SqFtHeated":1265.0,"YearBuilt":1984.0},"PostFlip":{"NumHouses":2.0,"Price":172450.0,"Beds":3.0,"FullBaths":2.0,"HalfBaths":0.0,"SqFtHeated":1265.0,"YearBuilt":1984.0},"RoiPurchase":0.0,"RoiSold":0.0},{"City":"ORLANDO","Zipcode":"32829","SubDivision":"CHICKASAW WOODS","PreFlip":{"NumHouses":2.0,"Price":132750.0,"Beds":3.0,"FullBaths":2.0,"HalfBaths":0.0,"SqFtHeated":1478.0,"YearBuilt":1976.0},"PostFlip":{"NumHouses":2.0,"Price":166750.0,"Beds":3.0,"FullBaths":2.0,"HalfBaths":0.0,"SqFtHeated":1475.0,"YearBuilt":1976.0},"RoiPurchase":0.0,"RoiSold":0.0},{"City":"ORLANDO","Zipcode":"33813, 32818","SubDivision":"COLONY","PreFlip":{"NumHouses":2.0,"Price":167750.0,"Beds":3.0,"FullBaths":2.0,"HalfBaths":0.0,"SqFtHeated":1890.0,"YearBuilt":1994.0},"PostFlip":{"NumHouses":2.0,"Price":208000.0,"Beds":3.0,"FullBaths":2.0,"HalfBaths":0.0,"SqFtHeated":1890.0,"YearBuilt":1994.0},"RoiPurchase":0.0,"RoiSold":0.0},{"City":"ORLANDO","Zipcode":"32806","SubDivision":"DOVER SHORES","PreFlip":{"NumHouses":4.0,"Price":153431.0,"Beds":2.0,"FullBaths":2.0,"HalfBaths":0.0,"SqFtHeated":1069.0,"YearBuilt":1467.0},"PostFlip":{"NumHouses":4.0,"Price":264875.0,"Beds":2.0,"FullBaths":2.0,"HalfBaths":0.0,"SqFtHeated":1098.0,"YearBuilt":1467.0},"RoiPurchase":0.0,"RoiSold":0.0},{"City":"ORLANDO","Zipcode":"32822","SubDivision":"EAST ORLANDO","PreFlip":{"NumHouses":7.0,"Price":92120.57,"Beds":1.0,"FullBaths":1.0,"HalfBaths":0.0,"SqFtHeated":602.0,"YearBuilt":845.0},"PostFlip":{"NumHouses":7.0,"Price":151192.86,"Beds":1.0,"FullBaths":1.0,"HalfBaths":0.0,"SqFtHeated":602.0,"YearBuilt":845.0},"RoiPurchase":0.0,"RoiSold":0.0},{"City":"ORLANDO","Zipcode":"32807","SubDivision":"ENGELWOOD PARK","PreFlip":{"NumHouses":3.0,"Price":82333.33,"Beds":4.0,"FullBaths":1.0,"HalfBaths":1.0,"SqFtHeated":1298.0,"YearBuilt":1961.0},"PostFlip":{"NumHouses":3.0,"Price":153633.33,"Beds":4.0,"FullBaths":2.0,"HalfBaths":1.0,"SqFtHeated":1298.0,"YearBuilt":1961.0},"RoiPurchase":0.0,"RoiSold":0.0},{"City":"ORLANDO","Zipcode":"32822","SubDivision":"HARBOR BEND","PreFlip":{"NumHouses":2.0,"Price":128887.5,"Beds":3.0,"FullBaths":2.0,"HalfBaths":0.0,"SqFtHeated":1249.0,"YearBuilt":2000.0},"PostFlip":{"NumHouses":2.0,"Price":169500.0,"Beds":3.0,"FullBaths":2.0,"HalfBaths":0.0,"SqFtHeated":1249.0,"YearBuilt":2000.0},"RoiPurchase":0.0,"RoiSold":0.0},{"City":"ORLANDO","Zipcode":"32818","SubDivision":"HIAWASSEE HILLS","PreFlip":{"NumHouses":3.0,"Price":86622.67,"Beds":3.0,"FullBaths":2.0,"HalfBaths":0.0,"SqFtHeated":1545.0,"YearBuilt":1986.0},"PostFlip":{"NumHouses":3.0,"Price":141966.67,"Beds":3.0,"FullBaths":2.0,"HalfBaths":0.0,"SqFtHeated":1545.0,"YearBuilt":1986.0},"RoiPurchase":0.0,"RoiSold":0.0},{"City":"ORLANDO","Zipcode":"32818","SubDivision":"HIAWASSEE OAKS","PreFlip":{"NumHouses":2.0,"Price":142000.0,"Beds":4.0,"FullBaths":2.0,"HalfBaths":0.0,"SqFtHeated":2442.0,"YearBuilt":1989.0},"PostFlip":{"NumHouses":2.0,"Price":201500.0,"Beds":4.0,"FullBaths":2.0,"HalfBaths":0.0,"SqFtHeated":2442.0,"YearBuilt":1989.0},"RoiPurchase":0.0,"RoiSold":0.0},{"City":"ORLANDO","Zipcode":"32837","SubDivision":"HUNTERS CREEK TR","PreFlip":{"NumHouses":7.0,"Price":259830.57,"Beds":4.0,"FullBaths":3.0,"HalfBaths":0.0,"SqFtHeated":2651.0,"YearBuilt":1993.0},"PostFlip":{"NumHouses":7.0,"Price":358639.29,"Beds":4.0,"FullBaths":3.0,"HalfBaths":0.0,"SqFtHeated":2651.0,"YearBuilt":1993.0},"RoiPurchase":0.0,"RoiSold":0.0},{"City":"ORLANDO","Zipcode":"32810","SubDivision":"KINGSWOOD MANOR","PreFlip":{"NumHouses":3.0,"Price":90333.33,"Beds":2.0,"FullBaths":1.0,"HalfBaths":0.0,"SqFtHeated":936.0,"YearBuilt":1314.0},"PostFlip":{"NumHouses":3.0,"Price":164000.0,"Beds":2.0,"FullBaths":1.0,"HalfBaths":0.0,"SqFtHeated":936.0,"YearBuilt":1314.0},"RoiPurchase":0.0,"RoiSold":0.0},{"City":"ORLANDO","Zipcode":"32808","SubDivision":"LONDONDERRY HILLS","PreFlip":{"NumHouses":3.0,"Price":44948.0,"Beds":2.0,"FullBaths":1.0,"HalfBaths":1.0,"SqFtHeated":1040.0,"YearBuilt":1310.0},"PostFlip":{"NumHouses":3.0,"Price":93000.0,"Beds":2.0,"FullBaths":1.0,"HalfBaths":0.0,"SqFtHeated":1082.0,"YearBuilt":1310.0},"RoiPurchase":0.0,"RoiSold":0.0},{"City":"ORLANDO","Zipcode":"32824","SubDivision":"MEADOW WOODS VILLAGE","PreFlip":{"NumHouses":2.0,"Price":123750.0,"Beds":4.0,"FullBaths":2.0,"HalfBaths":0.0,"SqFtHeated":1676.0,"YearBuilt":1988.0},"PostFlip":{"NumHouses":2.0,"Price":205750.0,"Beds":4.0,"FullBaths":2.0,"HalfBaths":0.0,"SqFtHeated":1676.0,"YearBuilt":1988.0},"RoiPurchase":0.0,"RoiSold":0.0},{"City":"ORLANDO","Zipcode":"33813, 32750, 32824","SubDivision":"MEADOWS","PreFlip":{"NumHouses":3.0,"Price":90700.0,"Beds":3.0,"FullBaths":2.0,"HalfBaths":0.0,"SqFtHeated":1310.0,"YearBuilt":1983.0},"PostFlip":{"NumHouses":3.0,"Price":166500.0,"Beds":3.0,"FullBaths":2.0,"HalfBaths":0.0,"SqFtHeated":1409.0,"YearBuilt":1983.0},"RoiPurchase":0.0,"RoiSold":0.0},{"City":"ORLANDO","Zipcode":"32825","SubDivision":"PINE MEADOWS","PreFlip":{"NumHouses":2.0,"Price":140000.0,"Beds":3.0,"FullBaths":2.0,"HalfBaths":0.0,"SqFtHeated":1926.0,"YearBuilt":1988.0},"PostFlip":{"NumHouses":2.0,"Price":200500.0,"Beds":3.0,"FullBaths":2.0,"HalfBaths":0.0,"SqFtHeated":1926.0,"YearBuilt":1988.0},"RoiPurchase":0.0,"RoiSold":0.0},{"City":"ORLANDO","Zipcode":"32811","SubDivision":"RICHMOND HEIGHTS","PreFlip":{"NumHouses":2.0,"Price":16800.0,"Beds":3.0,"FullBaths":1.0,"HalfBaths":0.0,"SqFtHeated":1106.0,"YearBuilt":1966.0},"PostFlip":{"NumHouses":2.0,"Price":37000.0,"Beds":3.0,"FullBaths":1.0,"HalfBaths":0.0,"SqFtHeated":1106.0,"YearBuilt":1966.0},"RoiPurchase":0.0,"RoiSold":0.0},{"City":"ORLANDO","Zipcode":"32808","SubDivision":"ROBINSWOOD","PreFlip":{"NumHouses":4.0,"Price":42875.0,"Beds":3.0,"FullBaths":2.0,"HalfBaths":0.0,"SqFtHeated":1483.0,"YearBuilt":1958.0},"PostFlip":{"NumHouses":4.0,"Price":105750.0,"Beds":4.0,"FullBaths":2.0,"HalfBaths":0.0,"SqFtHeated":1483.0,"YearBuilt":1958.0},"RoiPurchase":0.0,"RoiSold":0.0},{"City":"ORLANDO","Zipcode":"32819","SubDivision":"SAND LAKE HILLS","PreFlip":{"NumHouses":2.0,"Price":199500.0,"Beds":4.0,"FullBaths":2.0,"HalfBaths":0.0,"SqFtHeated":1790.0,"YearBuilt":1978.0},"PostFlip":{"NumHouses":2.0,"Price":267450.0,"Beds":4.0,"FullBaths":2.0,"HalfBaths":0.0,"SqFtHeated":1790.0,"YearBuilt":1978.0},"RoiPurchase":0.0,"RoiSold":0.0},{"City":"ORLANDO","Zipcode":"32808","SubDivision":"SIGNAL HILL","PreFlip":{"NumHouses":2.0,"Price":70000.0,"Beds":3.0,"FullBaths":2.0,"HalfBaths":0.0,"SqFtHeated":1640.0,"YearBuilt":1974.0},"PostFlip":{"NumHouses":2.0,"Price":132000.0,"Beds":4.0,"FullBaths":2.0,"HalfBaths":0.0,"SqFtHeated":1640.0,"YearBuilt":1974.0},"RoiPurchase":0.0,"RoiSold":0.0},{"City":"ORLANDO","Zipcode":"32818","SubDivision":"SILVER RIDGE","PreFlip":{"NumHouses":3.0,"Price":121166.67,"Beds":3.0,"FullBaths":2.0,"HalfBaths":0.0,"SqFtHeated":1630.0,"YearBuilt":1989.0},"PostFlip":{"NumHouses":3.0,"Price":170169.67,"Beds":3.0,"FullBaths":2.0,"HalfBaths":0.0,"SqFtHeated":1630.0,"YearBuilt":1989.0},"RoiPurchase":0.0,"RoiSold":0.0},{"City":"ORLANDO","Zipcode":"32837","SubDivision":"SKY LAKE SOUTH","PreFlip":{"NumHouses":7.0,"Price":126314.29,"Beds":3.0,"FullBaths":2.0,"HalfBaths":0.0,"SqFtHeated":1332.0,"YearBuilt":1697.0},"PostFlip":{"NumHouses":7.0,"Price":179928.57,"Beds":3.0,"FullBaths":2.0,"HalfBaths":0.0,"SqFtHeated":1352.0,"YearBuilt":1697.0},"RoiPurchase":0.0,"RoiSold":0.0},{"City":"ORLANDO","Zipcode":"32837","SubDivision":"SOUTHCHASE","PreFlip":{"NumHouses":2.0,"Price":152577.0,"Beds":4.0,"FullBaths":2.0,"HalfBaths":0.0,"SqFtHeated":1480.0,"YearBuilt":1992.0},"PostFlip":{"NumHouses":2.0,"Price":200000.0,"Beds":3.0,"FullBaths":2.0,"HalfBaths":0.0,"SqFtHeated":1480.0,"YearBuilt":1992.0},"RoiPurchase":0.0,"RoiSold":0.0},{"City":"ORLANDO","Zipcode":"32804","SubDivision":"SUNSHINE GARDENS","PreFlip":{"NumHouses":7.0,"Price":97541.14,"Beds":1.0,"FullBaths":1.0,"HalfBaths":0.0,"SqFtHeated":589.0,"YearBuilt":839.0},"PostFlip":{"NumHouses":7.0,"Price":190714.29,"Beds":1.0,"FullBaths":1.0,"HalfBaths":0.0,"SqFtHeated":624.0,"YearBuilt":839.0},"RoiPurchase":0.0,"RoiSold":0.0},{"City":"ORLANDO","Zipcode":"32817","SubDivision":"WATERMILL","PreFlip":{"NumHouses":3.0,"Price":170066.67,"Beds":2.0,"FullBaths":1.0,"HalfBaths":0.0,"SqFtHeated":1221.0,"YearBuilt":1323.0},"PostFlip":{"NumHouses":3.0,"Price":247333.33,"Beds":2.0,"FullBaths":1.0,"HalfBaths":0.0,"SqFtHeated":1221.0,"YearBuilt":1323.0},"RoiPurchase":0.0,"RoiSold":0.0},{"City":"OVIEDO","Zipcode":"32765","SubDivision":"ALAFAYA WOODS","PreFlip":{"NumHouses":3.0,"Price":132291.67,"Beds":3.0,"FullBaths":2.0,"HalfBaths":0.0,"SqFtHeated":1396.0,"YearBuilt":1987.0},"PostFlip":{"NumHouses":3.0,"Price":200333.33,"Beds":3.0,"FullBaths":2.0,"HalfBaths":0.0,"SqFtHeated":1396.0,"YearBuilt":1987.0},"RoiPurchase":0.0,"RoiSold":0.0},{"City":"POINCIANA","Zipcode":"34759","SubDivision":"POINCIANA NBRHD","PreFlip":{"NumHouses":5.0,"Price":68500.0,"Beds":1.0,"FullBaths":1.0,"HalfBaths":0.0,"SqFtHeated":454.0,"YearBuilt":793.0},"PostFlip":{"NumHouses":5.0,"Price":115200.0,"Beds":1.0,"FullBaths":1.0,"HalfBaths":0.0,"SqFtHeated":475.0,"YearBuilt":793.0},"RoiPurchase":0.0,"RoiSold":0.0},{"City":"SAINT CLOUD","Zipcode":"32707, 34772","SubDivision":"CAMELOT","PreFlip":{"NumHouses":2.0,"Price":212000.0,"Beds":3.0,"FullBaths":2.0,"HalfBaths":0.0,"SqFtHeated":1979.0,"YearBuilt":1983.0},"PostFlip":{"NumHouses":2.0,"Price":259000.0,"Beds":4.0,"FullBaths":2.0,"HalfBaths":0.0,"SqFtHeated":1979.0,"YearBuilt":1983.0},"RoiPurchase":0.0,"RoiSold":0.0},{"City":"SAINT CLOUD","Zipcode":"34772","SubDivision":"CANOE CREEK WOODS","PreFlip":{"NumHouses":3.0,"Price":121666.67,"Beds":3.0,"FullBaths":2.0,"HalfBaths":0.0,"SqFtHeated":1416.0,"YearBuilt":1990.0},"PostFlip":{"NumHouses":3.0,"Price":189966.67,"Beds":3.0,"FullBaths":2.0,"HalfBaths":0.0,"SqFtHeated":1416.0,"YearBuilt":1990.0},"RoiPurchase":0.0,"RoiSold":0.0},{"City":"SAINT CLOUD","Zipcode":"33860, 34769","SubDivision":"PINE LAKE","PreFlip":{"NumHouses":3.0,"Price":91875.0,"Beds":3.0,"FullBaths":2.0,"HalfBaths":0.0,"SqFtHeated":1677.0,"YearBuilt":1976.0},"PostFlip":{"NumHouses":3.0,"Price":166833.33,"Beds":3.0,"FullBaths":2.0,"HalfBaths":0.0,"SqFtHeated":1677.0,"YearBuilt":1976.0},"RoiPurchase":0.0,"RoiSold":0.0},{"City":"SAINT CLOUD","Zipcode":"34769, 34772","SubDivision":"ST CLOUD","PreFlip":{"NumHouses":5.0,"Price":71640.0,"Beds":1.0,"FullBaths":1.0,"HalfBaths":0.0,"SqFtHeated":480.0,"YearBuilt":788.0},"PostFlip":{"NumHouses":5.0,"Price":141000.0,"Beds":1.0,"FullBaths":1.0,"HalfBaths":0.0,"SqFtHeated":509.0,"YearBuilt":788.0},"RoiPurchase":0.0,"RoiSold":0.0},{"City":"WINTER HAVEN","Zipcode":"33884","SubDivision":"GARDEN GROVE","PreFlip":{"NumHouses":2.0,"Price":62000.0,"Beds":3.0,"FullBaths":2.0,"HalfBaths":0.0,"SqFtHeated":1300.0,"YearBuilt":1962.0},"PostFlip":{"NumHouses":2.0,"Price":126950.0,"Beds":3.0,"FullBaths":2.0,"HalfBaths":0.0,"SqFtHeated":1432.0,"YearBuilt":1962.0},"RoiPurchase":0.0,"RoiSold":0.0},{"City":"WINTER HAVEN","Zipcode":"33881","SubDivision":"INWOOD","PreFlip":{"NumHouses":2.0,"Price":42750.0,"Beds":3.0,"FullBaths":1.0,"HalfBaths":0.0,"SqFtHeated":1292.0,"YearBuilt":1945.0},"PostFlip":{"NumHouses":2.0,"Price":69250.0,"Beds":3.0,"FullBaths":1.0,"HalfBaths":0.0,"SqFtHeated":1292.0,"YearBuilt":1945.0},"RoiPurchase":0.0,"RoiSold":0.0},{"City":"WINTER HAVEN","Zipcode":"32773, 33880","SubDivision":"WOODMERE","PreFlip":{"NumHouses":2.0,"Price":65250.0,"Beds":4.0,"FullBaths":2.0,"HalfBaths":0.0,"SqFtHeated":1508.0,"YearBuilt":1965.0},"PostFlip":{"NumHouses":2.0,"Price":119000.0,"Beds":4.0,"FullBaths":2.0,"HalfBaths":0.0,"SqFtHeated":1459.0,"YearBuilt":1965.0},"RoiPurchase":0.0,"RoiSold":0.0},{"City":"WINTER PARK","Zipcode":"32792","SubDivision":"EASTBROOK SUB","PreFlip":{"NumHouses":3.0,"Price":136699.67,"Beds":4.0,"FullBaths":2.0,"HalfBaths":0.0,"SqFtHeated":1722.0,"YearBuilt":1966.0},"PostFlip":{"NumHouses":3.0,"Price":186833.33,"Beds":4.0,"FullBaths":2.0,"HalfBaths":0.0,"SqFtHeated":1722.0,"YearBuilt":1966.0},"RoiPurchase":0.0,"RoiSold":0.0},{"City":"WINTER PARK","Zipcode":"32712, 32789","SubDivision":"PINES","PreFlip":{"NumHouses":2.0,"Price":140250.0,"Beds":4.0,"FullBaths":2.0,"HalfBaths":0.0,"SqFtHeated":3136.0,"YearBuilt":1960.0},"PostFlip":{"NumHouses":2.0,"Price":227500.0,"Beds":4.0,"FullBaths":2.0,"HalfBaths":0.0,"SqFtHeated":3136.0,"YearBuilt":1960.0},"RoiPurchase":0.0,"RoiSold":0.0},{"City":"WINTER PARK","Zipcode":"32792","SubDivision":"WRENWOOD HEIGHTS","PreFlip":{"NumHouses":2.0,"Price":124500.0,"Beds":3.0,"FullBaths":2.0,"HalfBaths":0.0,"SqFtHeated":1700.0,"YearBuilt":1973.0},"PostFlip":{"NumHouses":2.0,"Price":218500.0,"Beds":4.0,"FullBaths":2.0,"HalfBaths":0.0,"SqFtHeated":1700.0,"YearBuilt":1973.0},"RoiPurchase":0.0,"RoiSold":0.0},{"City":"WINTER SPRINGS","Zipcode":"32708","SubDivision":"NORTH ORLANDO TERRACE","PreFlip":{"NumHouses":2.0,"Price":102467.0,"Beds":4.0,"FullBaths":2.0,"HalfBaths":0.0,"SqFtHeated":1424.0,"YearBuilt":1974.0},"PostFlip":{"NumHouses":2.0,"Price":172000.0,"Beds":4.0,"FullBaths":2.0,"HalfBaths":0.0,"SqFtHeated":1424.0,"YearBuilt":1974.0},"RoiPurchase":0.0,"RoiSold":0.0},{"City":"WINTER SPRINGS","Zipcode":"32708","SubDivision":"OAK FOREST","PreFlip":{"NumHouses":4.0,"Price":168595.75,"Beds":4.0,"FullBaths":2.0,"HalfBaths":0.0,"SqFtHeated":1883.0,"YearBuilt":1984.0},"PostFlip":{"NumHouses":4.0,"Price":268725.0,"Beds":4.0,"FullBaths":2.0,"HalfBaths":0.0,"SqFtHeated":1883.0,"YearBuilt":1984.0},"RoiPurchase":0.0,"RoiSold":0.0}]